datatransformationslibrary.py
datatransformationslibrary-0.1.2.dist-info/METADATA
datatransformationslibrary-0.1.2.dist-info/WHEEL
datatransformationslibrary-0.1.2.dist-info/RECORD
