Metadata-Version: 2.1
Name: datatransformationslibrary
Version: 0.1.2
Summary: 
Author: Your Name
Author-email: you@example.com
Requires-Python: >=3.9,<4.0
Classifier: Programming Language :: Python :: 3
Classifier: Programming Language :: Python :: 3.9
Classifier: Programming Language :: Python :: 3.10
Classifier: Programming Language :: Python :: 3.11
Requires-Dist: numpy (>=1.18.0,<2.0.0)
Requires-Dist: pytest (>=7.4.0,<8.0.0)
